geometrydash/__init__.py
geometrydash/errors.py
geometrydash/geometrydash.py
geometrydash/objects.py
geometrydash/utils.py
geometrydash-1.0.0.dist-info/LICENSE
geometrydash-1.0.0.dist-info/METADATA
geometrydash-1.0.0.dist-info/WHEEL
geometrydash-1.0.0.dist-info/top_level.txt
geometrydash-1.0.0.dist-info/RECORD
